pyssql/__class.py
pyssql/__database.py
pyssql/__init__.py
pyssql/__types.py
pyssql-1.0.0.dist-info/LICENSE
pyssql-1.0.0.dist-info/METADATA
pyssql-1.0.0.dist-info/WHEEL
pyssql-1.0.0.dist-info/top_level.txt
pyssql-1.0.0.dist-info/RECORD
