Metadata-Version: 2.1
Name: pyssql
Version: 1.0.0
Summary: An sql module that requires no knowledge of sql syntax.
Home-page: https://github.com/Matthias1590/SimpleSql
Author: Matthias Wijnsma
Author-email: matthiasx95@gmail.com
License: MIT
Platform: UNKNOWN
Requires-Python: >=3.6
License-File: LICENSE
